{
  "id": "65030b70-92b4-4119-b8a6-e929328f48ac",
  "prevId": "00000000-0000-0000-0000-000000000000",
  "version": "7",
  "dialect": "postgresql",
  "tables": {
    "public.accounts": {
      "name": "accounts",
      "schema": "",
      "columns": {
        "id": {
          "name": "id",
          "type": "text",
          "primaryKey": true,
          "notNull": true
        },
        "account_id": {
          "name": "account_id",
          "type": "text",
          "primaryKey": false,
          "notNull": true
        },
        "provider_id": {
          "name": "provider_id",
          "type": "text",
          "primaryKey": false,
          "notNull": true
        },
        "user_id": {
          "name": "user_id",
          "type": "text",
          "primaryKey": false,
          "notNull": true
        },
        "access_token": {
          "name": "access_token",
          "type": "text",
          "primaryKey": false,
          "notNull": false
        },
        "refresh_token": {
          "name": "refresh_token",
          "type": "text",
          "primaryKey": false,
          "notNull": false
        },
        "id_token": {
          "name": "id_token",
          "type": "text",
          "primaryKey": false,
          "notNull": false
        },
        "access_token_expires_at": {
          "name": "access_token_expires_at",
          "type": "timestamp",
          "primaryKey": false,
          "notNull": false
        },
        "refresh_token_expires_at": {
          "name": "refresh_token_expires_at",
          "type": "timestamp",
          "primaryKey": false,
          "notNull": false
        },
        "scope": {
          "name": "scope",
          "type": "text",
          "primaryKey": false,
          "notNull": false
        },
        "password": {
          "name": "password",
          "type": "text",
          "primaryKey": false,
          "notNull": false
        },
        "created_at": {
          "name": "created_at",
          "type": "timestamp",
          "primaryKey": false,
          "notNull": true,
          "default": "now()"
        },
        "updated_at": {
          "name": "updated_at",
          "type": "timestamp",
          "primaryKey": false,
          "notNull": true
        }
      },
      "indexes": {},
      "foreignKeys": {
        "accounts_user_id_users_id_fk": {
          "name": "accounts_user_id_users_id_fk",
          "tableFrom": "accounts",
          "tableTo": "users",
          "columnsFrom": [
            "user_id"
          ],
          "columnsTo": [
            "id"
          ],
          "onDelete": "cascade",
          "onUpdate": "no action"
        }
      },
      "compositePrimaryKeys": {},
      "uniqueConstraints": {},
      "policies": {},
      "checkConstraints": {},
      "isRLSEnabled": false
    },
    "public.albums": {
      "name": "albums",
      "schema": "",
      "columns": {
        "id": {
          "name": "id",
          "type": "serial",
          "primaryKey": true,
          "notNull": true
        },
        "title": {
          "name": "title",
          "type": "varchar(255)",
          "primaryKey": false,
          "notNull": true
        },
        "artist_id": {
          "name": "artist_id",
          "type": "integer",
          "primaryKey": false,
          "notNull": true
        }
      },
      "indexes": {},
      "foreignKeys": {
        "album_artist_id_fkey": {
          "name": "album_artist_id_fkey",
          "tableFrom": "albums",
          "tableTo": "artists",
          "columnsFrom": [
            "artist_id"
          ],
          "columnsTo": [
            "id"
          ],
          "onDelete": "no action",
          "onUpdate": "no action"
        }
      },
      "compositePrimaryKeys": {},
      "uniqueConstraints": {},
      "policies": {},
      "checkConstraints": {},
      "isRLSEnabled": false
    },
    "public.artists": {
      "name": "artists",
      "schema": "",
      "columns": {
        "id": {
          "name": "id",
          "type": "serial",
          "primaryKey": true,
          "notNull": true
        },
        "name": {
          "name": "name",
          "type": "varchar(255)",
          "primaryKey": false,
          "notNull": true
        }
      },
      "indexes": {},
      "foreignKeys": {},
      "compositePrimaryKeys": {},
      "uniqueConstraints": {},
      "policies": {},
      "checkConstraints": {},
      "isRLSEnabled": false
    },
    "public.customers": {
      "name": "customers",
      "schema": "",
      "columns": {
        "id": {
          "name": "id",
          "type": "serial",
          "primaryKey": true,
          "notNull": true
        },
        "first_name": {
          "name": "first_name",
          "type": "varchar(255)",
          "primaryKey": false,
          "notNull": true
        },
        "last_name": {
          "name": "last_name",
          "type": "varchar(255)",
          "primaryKey": false,
          "notNull": true
        },
        "company": {
          "name": "company",
          "type": "varchar(255)",
          "primaryKey": false,
          "notNull": false
        },
        "address": {
          "name": "address",
          "type": "varchar(255)",
          "primaryKey": false,
          "notNull": false
        },
        "city": {
          "name": "city",
          "type": "varchar(255)",
          "primaryKey": false,
          "notNull": false
        },
        "state": {
          "name": "state",
          "type": "varchar(255)",
          "primaryKey": false,
          "notNull": false
        },
        "country": {
          "name": "country",
          "type": "varchar(255)",
          "primaryKey": false,
          "notNull": false
        },
        "postal_code": {
          "name": "postal_code",
          "type": "varchar(255)",
          "primaryKey": false,
          "notNull": false
        },
        "phone": {
          "name": "phone",
          "type": "varchar(255)",
          "primaryKey": false,
          "notNull": false
        },
        "fax": {
          "name": "fax",
          "type": "varchar(255)",
          "primaryKey": false,
          "notNull": false
        },
        "email": {
          "name": "email",
          "type": "varchar(255)",
          "primaryKey": false,
          "notNull": true
        },
        "support_rep_id": {
          "name": "support_rep_id",
          "type": "integer",
          "primaryKey": false,
          "notNull": false
        }
      },
      "indexes": {},
      "foreignKeys": {
        "customer_support_rep_id_fkey": {
          "name": "customer_support_rep_id_fkey",
          "tableFrom": "customers",
          "tableTo": "employees",
          "columnsFrom": [
            "support_rep_id"
          ],
          "columnsTo": [
            "id"
          ],
          "onDelete": "no action",
          "onUpdate": "no action"
        }
      },
      "compositePrimaryKeys": {},
      "uniqueConstraints": {},
      "policies": {},
      "checkConstraints": {},
      "isRLSEnabled": false
    },
    "public.employees": {
      "name": "employees",
      "schema": "",
      "columns": {
        "id": {
          "name": "id",
          "type": "serial",
          "primaryKey": true,
          "notNull": true
        },
        "first_name": {
          "name": "first_name",
          "type": "varchar(255)",
          "primaryKey": false,
          "notNull": true
        },
        "last_name": {
          "name": "last_name",
          "type": "varchar(255)",
          "primaryKey": false,
          "notNull": true
        },
        "title": {
          "name": "title",
          "type": "varchar(255)",
          "primaryKey": false,
          "notNull": false
        },
        "reports_to": {
          "name": "reports_to",
          "type": "integer",
          "primaryKey": false,
          "notNull": false
        },
        "birth_date": {
          "name": "birth_date",
          "type": "timestamp",
          "primaryKey": false,
          "notNull": false
        },
        "hire_date": {
          "name": "hire_date",
          "type": "timestamp",
          "primaryKey": false,
          "notNull": false
        },
        "address": {
          "name": "address",
          "type": "varchar(255)",
          "primaryKey": false,
          "notNull": false
        },
        "city": {
          "name": "city",
          "type": "varchar(255)",
          "primaryKey": false,
          "notNull": false
        },
        "state": {
          "name": "state",
          "type": "varchar(255)",
          "primaryKey": false,
          "notNull": false
        },
        "country": {
          "name": "country",
          "type": "varchar(255)",
          "primaryKey": false,
          "notNull": false
        },
        "postal_code": {
          "name": "postal_code",
          "type": "varchar(255)",
          "primaryKey": false,
          "notNull": false
        },
        "phone": {
          "name": "phone",
          "type": "varchar(255)",
          "primaryKey": false,
          "notNull": false
        },
        "fax": {
          "name": "fax",
          "type": "varchar(255)",
          "primaryKey": false,
          "notNull": false
        },
        "email": {
          "name": "email",
          "type": "varchar(255)",
          "primaryKey": false,
          "notNull": false
        }
      },
      "indexes": {},
      "foreignKeys": {
        "employee_reports_to_fkey": {
          "name": "employee_reports_to_fkey",
          "tableFrom": "employees",
          "tableTo": "employees",
          "columnsFrom": [
            "reports_to"
          ],
          "columnsTo": [
            "id"
          ],
          "onDelete": "no action",
          "onUpdate": "no action"
        }
      },
      "compositePrimaryKeys": {},
      "uniqueConstraints": {},
      "policies": {},
      "checkConstraints": {},
      "isRLSEnabled": false
    },
    "public.genres": {
      "name": "genres",
      "schema": "",
      "columns": {
        "id": {
          "name": "id",
          "type": "serial",
          "primaryKey": true,
          "notNull": true
        },
        "name": {
          "name": "name",
          "type": "varchar(255)",
          "primaryKey": false,
          "notNull": true
        }
      },
      "indexes": {},
      "foreignKeys": {},
      "compositePrimaryKeys": {},
      "uniqueConstraints": {},
      "policies": {},
      "checkConstraints": {},
      "isRLSEnabled": false
    },
    "public.invoice_lines": {
      "name": "invoice_lines",
      "schema": "",
      "columns": {
        "id": {
          "name": "id",
          "type": "serial",
          "primaryKey": true,
          "notNull": true
        },
        "invoice_id": {
          "name": "invoice_id",
          "type": "integer",
          "primaryKey": false,
          "notNull": true
        },
        "track_id": {
          "name": "track_id",
          "type": "integer",
          "primaryKey": false,
          "notNull": true
        },
        "unit_price": {
          "name": "unit_price",
          "type": "numeric(10, 2)",
          "primaryKey": false,
          "notNull": true
        },
        "quantity": {
          "name": "quantity",
          "type": "integer",
          "primaryKey": false,
          "notNull": true
        }
      },
      "indexes": {},
      "foreignKeys": {
        "invoice_line_invoice_id_fkey": {
          "name": "invoice_line_invoice_id_fkey",
          "tableFrom": "invoice_lines",
          "tableTo": "invoices",
          "columnsFrom": [
            "invoice_id"
          ],
          "columnsTo": [
            "id"
          ],
          "onDelete": "no action",
          "onUpdate": "no action"
        },
        "invoice_line_track_id_fkey": {
          "name": "invoice_line_track_id_fkey",
          "tableFrom": "invoice_lines",
          "tableTo": "tracks",
          "columnsFrom": [
            "track_id"
          ],
          "columnsTo": [
            "id"
          ],
          "onDelete": "no action",
          "onUpdate": "no action"
        }
      },
      "compositePrimaryKeys": {},
      "uniqueConstraints": {},
      "policies": {},
      "checkConstraints": {},
      "isRLSEnabled": false
    },
    "public.invoices": {
      "name": "invoices",
      "schema": "",
      "columns": {
        "id": {
          "name": "id",
          "type": "serial",
          "primaryKey": true,
          "notNull": true
        },
        "customer_id": {
          "name": "customer_id",
          "type": "integer",
          "primaryKey": false,
          "notNull": true
        },
        "invoice_date": {
          "name": "invoice_date",
          "type": "timestamp",
          "primaryKey": false,
          "notNull": true
        },
        "billing_address": {
          "name": "billing_address",
          "type": "varchar(255)",
          "primaryKey": false,
          "notNull": false
        },
        "billing_city": {
          "name": "billing_city",
          "type": "varchar(255)",
          "primaryKey": false,
          "notNull": false
        },
        "billing_state": {
          "name": "billing_state",
          "type": "varchar(255)",
          "primaryKey": false,
          "notNull": false
        },
        "billing_country": {
          "name": "billing_country",
          "type": "varchar(255)",
          "primaryKey": false,
          "notNull": false
        },
        "billing_postal_code": {
          "name": "billing_postal_code",
          "type": "varchar(255)",
          "primaryKey": false,
          "notNull": false
        },
        "total": {
          "name": "total",
          "type": "numeric(10, 2)",
          "primaryKey": false,
          "notNull": true
        }
      },
      "indexes": {},
      "foreignKeys": {
        "invoice_customer_id_fkey": {
          "name": "invoice_customer_id_fkey",
          "tableFrom": "invoices",
          "tableTo": "customers",
          "columnsFrom": [
            "customer_id"
          ],
          "columnsTo": [
            "id"
          ],
          "onDelete": "no action",
          "onUpdate": "no action"
        }
      },
      "compositePrimaryKeys": {},
      "uniqueConstraints": {},
      "policies": {},
      "checkConstraints": {},
      "isRLSEnabled": false
    },
    "public.media_types": {
      "name": "media_types",
      "schema": "",
      "columns": {
        "id": {
          "name": "id",
          "type": "serial",
          "primaryKey": true,
          "notNull": true
        },
        "name": {
          "name": "name",
          "type": "varchar(255)",
          "primaryKey": false,
          "notNull": true
        }
      },
      "indexes": {},
      "foreignKeys": {},
      "compositePrimaryKeys": {},
      "uniqueConstraints": {},
      "policies": {},
      "checkConstraints": {},
      "isRLSEnabled": false
    },
    "public.playlist_tracks": {
      "name": "playlist_tracks",
      "schema": "",
      "columns": {
        "playlist_id": {
          "name": "playlist_id",
          "type": "integer",
          "primaryKey": false,
          "notNull": true
        },
        "track_id": {
          "name": "track_id",
          "type": "integer",
          "primaryKey": false,
          "notNull": true
        }
      },
      "indexes": {},
      "foreignKeys": {
        "playlist_track_playlist_id_fkey": {
          "name": "playlist_track_playlist_id_fkey",
          "tableFrom": "playlist_tracks",
          "tableTo": "playlists",
          "columnsFrom": [
            "playlist_id"
          ],
          "columnsTo": [
            "id"
          ],
          "onDelete": "no action",
          "onUpdate": "no action"
        },
        "playlist_track_track_id_fkey": {
          "name": "playlist_track_track_id_fkey",
          "tableFrom": "playlist_tracks",
          "tableTo": "tracks",
          "columnsFrom": [
            "track_id"
          ],
          "columnsTo": [
            "id"
          ],
          "onDelete": "no action",
          "onUpdate": "no action"
        }
      },
      "compositePrimaryKeys": {
        "playlist_tracks_pkey": {
          "name": "playlist_tracks_pkey",
          "columns": [
            "playlist_id",
            "track_id"
          ]
        }
      },
      "uniqueConstraints": {},
      "policies": {},
      "checkConstraints": {},
      "isRLSEnabled": false
    },
    "public.playlists": {
      "name": "playlists",
      "schema": "",
      "columns": {
        "id": {
          "name": "id",
          "type": "serial",
          "primaryKey": true,
          "notNull": true
        },
        "name": {
          "name": "name",
          "type": "varchar(255)",
          "primaryKey": false,
          "notNull": true
        }
      },
      "indexes": {},
      "foreignKeys": {},
      "compositePrimaryKeys": {},
      "uniqueConstraints": {},
      "policies": {},
      "checkConstraints": {},
      "isRLSEnabled": false
    },
    "public.sessions": {
      "name": "sessions",
      "schema": "",
      "columns": {
        "id": {
          "name": "id",
          "type": "text",
          "primaryKey": true,
          "notNull": true
        },
        "expires_at": {
          "name": "expires_at",
          "type": "timestamp",
          "primaryKey": false,
          "notNull": true
        },
        "token": {
          "name": "token",
          "type": "text",
          "primaryKey": false,
          "notNull": true
        },
        "created_at": {
          "name": "created_at",
          "type": "timestamp",
          "primaryKey": false,
          "notNull": true,
          "default": "now()"
        },
        "updated_at": {
          "name": "updated_at",
          "type": "timestamp",
          "primaryKey": false,
          "notNull": true
        },
        "ip_address": {
          "name": "ip_address",
          "type": "text",
          "primaryKey": false,
          "notNull": false
        },
        "user_agent": {
          "name": "user_agent",
          "type": "text",
          "primaryKey": false,
          "notNull": false
        },
        "user_id": {
          "name": "user_id",
          "type": "text",
          "primaryKey": false,
          "notNull": true
        }
      },
      "indexes": {},
      "foreignKeys": {
        "sessions_user_id_users_id_fk": {
          "name": "sessions_user_id_users_id_fk",
          "tableFrom": "sessions",
          "tableTo": "users",
          "columnsFrom": [
            "user_id"
          ],
          "columnsTo": [
            "id"
          ],
          "onDelete": "cascade",
          "onUpdate": "no action"
        }
      },
      "compositePrimaryKeys": {},
      "uniqueConstraints": {
        "sessions_token_unique": {
          "name": "sessions_token_unique",
          "nullsNotDistinct": false,
          "columns": [
            "token"
          ]
        }
      },
      "policies": {},
      "checkConstraints": {},
      "isRLSEnabled": false
    },
    "public.tracks": {
      "name": "tracks",
      "schema": "",
      "columns": {
        "id": {
          "name": "id",
          "type": "serial",
          "primaryKey": true,
          "notNull": true
        },
        "name": {
          "name": "name",
          "type": "varchar(200)",
          "primaryKey": false,
          "notNull": true
        },
        "album_id": {
          "name": "album_id",
          "type": "integer",
          "primaryKey": false,
          "notNull": false
        },
        "media_type_id": {
          "name": "media_type_id",
          "type": "integer",
          "primaryKey": false,
          "notNull": true
        },
        "genre_id": {
          "name": "genre_id",
          "type": "integer",
          "primaryKey": false,
          "notNull": false
        },
        "composer": {
          "name": "composer",
          "type": "varchar(220)",
          "primaryKey": false,
          "notNull": false
        },
        "milliseconds": {
          "name": "milliseconds",
          "type": "integer",
          "primaryKey": false,
          "notNull": true
        },
        "bytes": {
          "name": "bytes",
          "type": "integer",
          "primaryKey": false,
          "notNull": false
        },
        "unit_price": {
          "name": "unit_price",
          "type": "numeric(10, 2)",
          "primaryKey": false,
          "notNull": true
        }
      },
      "indexes": {},
      "foreignKeys": {
        "track_album_id_fkey": {
          "name": "track_album_id_fkey",
          "tableFrom": "tracks",
          "tableTo": "albums",
          "columnsFrom": [
            "album_id"
          ],
          "columnsTo": [
            "id"
          ],
          "onDelete": "no action",
          "onUpdate": "no action"
        },
        "track_genre_id_fkey": {
          "name": "track_genre_id_fkey",
          "tableFrom": "tracks",
          "tableTo": "genres",
          "columnsFrom": [
            "genre_id"
          ],
          "columnsTo": [
            "id"
          ],
          "onDelete": "no action",
          "onUpdate": "no action"
        },
        "track_media_type_id_fkey": {
          "name": "track_media_type_id_fkey",
          "tableFrom": "tracks",
          "tableTo": "media_types",
          "columnsFrom": [
            "media_type_id"
          ],
          "columnsTo": [
            "id"
          ],
          "onDelete": "no action",
          "onUpdate": "no action"
        }
      },
      "compositePrimaryKeys": {},
      "uniqueConstraints": {},
      "policies": {},
      "checkConstraints": {},
      "isRLSEnabled": false
    },
    "public.users": {
      "name": "users",
      "schema": "",
      "columns": {
        "id": {
          "name": "id",
          "type": "text",
          "primaryKey": true,
          "notNull": true
        },
        "name": {
          "name": "name",
          "type": "text",
          "primaryKey": false,
          "notNull": true
        },
        "email": {
          "name": "email",
          "type": "text",
          "primaryKey": false,
          "notNull": true
        },
        "email_verified": {
          "name": "email_verified",
          "type": "boolean",
          "primaryKey": false,
          "notNull": true,
          "default": false
        },
        "image": {
          "name": "image",
          "type": "text",
          "primaryKey": false,
          "notNull": false
        },
        "created_at": {
          "name": "created_at",
          "type": "timestamp",
          "primaryKey": false,
          "notNull": true,
          "default": "now()"
        },
        "updated_at": {
          "name": "updated_at",
          "type": "timestamp",
          "primaryKey": false,
          "notNull": true,
          "default": "now()"
        }
      },
      "indexes": {},
      "foreignKeys": {},
      "compositePrimaryKeys": {},
      "uniqueConstraints": {
        "users_email_unique": {
          "name": "users_email_unique",
          "nullsNotDistinct": false,
          "columns": [
            "email"
          ]
        }
      },
      "policies": {},
      "checkConstraints": {},
      "isRLSEnabled": false
    },
    "public.verifications": {
      "name": "verifications",
      "schema": "",
      "columns": {
        "id": {
          "name": "id",
          "type": "text",
          "primaryKey": true,
          "notNull": true
        },
        "identifier": {
          "name": "identifier",
          "type": "text",
          "primaryKey": false,
          "notNull": true
        },
        "value": {
          "name": "value",
          "type": "text",
          "primaryKey": false,
          "notNull": true
        },
        "expires_at": {
          "name": "expires_at",
          "type": "timestamp",
          "primaryKey": false,
          "notNull": true
        },
        "created_at": {
          "name": "created_at",
          "type": "timestamp",
          "primaryKey": false,
          "notNull": true,
          "default": "now()"
        },
        "updated_at": {
          "name": "updated_at",
          "type": "timestamp",
          "primaryKey": false,
          "notNull": true,
          "default": "now()"
        }
      },
      "indexes": {},
      "foreignKeys": {},
      "compositePrimaryKeys": {},
      "uniqueConstraints": {},
      "policies": {},
      "checkConstraints": {},
      "isRLSEnabled": false
    }
  },
  "enums": {},
  "schemas": {},
  "sequences": {},
  "roles": {},
  "policies": {},
  "views": {},
  "_meta": {
    "columns": {},
    "schemas": {},
    "tables": {}
  }
}